{"friday": [{"date_arr": "Fr, 12/27", "date_dep": "Fr, 12/27", "from": "San Antonio de Monterrey", "from_link": "//horariodebuses.com/cr/busstop.php?city=San%20Antonio%20de%20Monterrey&lang=en&ruta=bu,f&comp=Transp%20S%20Carlos%20-%20S%20Jose&tele=2460-5032&cweb=&ort=&lon=0&lat=0", "remarks": " Journey duration: 4:15h Bus:  comes   from Guatuso ", "time_arr": "13:00", "time_dep": "08:45", "to": "San José", "to_lat": "9.939262", "to_link": "//horariodebuses.com/cr/busstop.php?city=San%20Jose&lang=en&ruta=bu,t&comp=Transp%20S%20Carlos%20-%20S%20Jose&tele=2460-5032&cweb=&ort=Calle%2012%20Av%207-9&lon=-84.08383&lat=9.939262", "to_lon": "84.08383", "trans_name": "Transp S Carlos - S José", "trans_tel": "2460-5032"}, {"date_arr": "Fr, 12/27", "date_dep": "Fr, 12/27", "from": "San Antonio de Monterrey", "from_link": "//horariodebuses.com/cr/busstop.php?city=San%20Antonio%20de%20Monterrey&lang=en&ruta=bu,f&comp=Transp%20S%20Carlos%20-%20S%20Jose&tele=2460-5032&cweb=&ort=&lon=0&lat=0", "remarks": " Journey duration: 4:15h Bus:  comes   from Guatuso ", "time_arr": "16:30", "time_dep": "12:15", "to": "San José", "to_lat": "9.939262", "to_link": "//horariodebuses.com/cr/busstop.php?city=San%20Jose&lang=en&ruta=bu,t&comp=Transp%20S%20Carlos%20-%20S%20Jose&tele=2460-5032&cweb=&ort=Calle%2012%20Av%207-9&lon=-84.08383&lat=9.939262", "to_lon": "84.08383", "trans_name": "Transp S Carlos - S José", "trans_tel": "2460-5032"}, {"date_arr": "Fr, 12/27", "date_dep": "Fr, 12/27", "from": "San Antonio de Monterrey", "from_link": "//horariodebuses.com/cr/busstop.php?city=San%20Antonio%20de%20Monterrey&lang=en&ruta=bu,f&comp=Transp%20S%20Carlos%20-%20S%20Jose&tele=2460-5032&cweb=&ort=&lon=0&lat=0", "remarks": " Journey duration: 4:15h Bus:  comes   from Guatuso ", "time_arr": "20:00", "time_dep": "15:45", "to": "San José", "to_lat": "9.939262", "to_link": "//horariodebuses.com/cr/busstop.php?city=San%20Jose&lang=en&ruta=bu,t&comp=Transp%20S%20Carlos%20-%20S%20Jose&tele=2460-5032&cweb=&ort=Calle%2012%20Av%207-9&lon=-84.08383&lat=9.939262", "to_lon": "84.08383", "trans_name": "Transp S Carlos - S José", "trans_tel": "2460-5032"}], "from": "San Antonio de Monterrey", "monday": [{"date_arr": "Mo, 12/23", "date_dep": "Mo, 12/23", "from": "San Antonio de Monterrey", "from_link": "//horariodebuses.com/cr/busstop.php?city=San%20Antonio%20de%20Monterrey&lang=en&ruta=bu,f&comp=Transp%20S%20Carlos%20-%20S%20Jose&tele=2460-5032&cweb=&ort=&lon=0&lat=0", "remarks": " Journey duration: 4:15h Bus:  comes   from Guatuso ", "time_arr": "13:00", "time_dep": "08:45", "to": "San José", "to_lat": "9.939262", "to_link": "//horariodebuses.com/cr/busstop.php?city=San%20Jose&lang=en&ruta=bu,t&comp=Transp%20S%20Carlos%20-%20S%20Jose&tele=2460-5032&cweb=&ort=Calle%2012%20Av%207-9&lon=-84.08383&lat=9.939262", "to_lon": "84.08383", "trans_name": "Transp S Carlos - S José", "trans_tel": "2460-5032"}, {"date_arr": "Mo, 12/23", "date_dep": "Mo, 12/23", "from": "San Antonio de Monterrey", "from_link": "//horariodebuses.com/cr/busstop.php?city=San%20Antonio%20de%20Monterrey&lang=en&ruta=bu,f&comp=Transnorte%20de%20Upala&tele=2470-0743&cweb=www.transnortecr.com&ort=&lon=0&lat=0", "remarks": " Journey duration: 4:15h Bus:  comes   from Upala ", "time_arr": "15:00", "time_dep": "10:45", "to": "San José", "to_lat": "9.93882880034025", "to_link": "//horariodebuses.com/cr/busstop.php?city=San%20Jose&lang=en&ruta=bu,t&comp=Transnorte%20de%20Upala&tele=2470-0743&cweb=www.transnortecr.com&ort=Calle%2012,%20Av%207-9&lon=-84.0838730335236&lat=9.93882880034025", "to_lon": "84.0838730335236", "trans_link": "//www.transnortecr.com", "trans_name": "Transnorte de Upala", "trans_tel": "2470-0743"}, {"date_arr": "Mo, 12/23", "date_dep": "Mo, 12/23", "from": "San Antonio de Monterrey", "from_link": "//horariodebuses.com/cr/busstop.php?city=San%20Antonio%20de%20Monterrey&lang=en&ruta=bu,f&comp=Transp%20S%20Carlos%20-%20S%20Jose&tele=2460-5032&cweb=&ort=&lon=0&lat=0", "remarks": " Journey duration: 4:15h Bus:  comes   from Guatuso ", "time_arr": "16:30", "time_dep": "12:15", "to": "San José", "to_lat": "9.939262", "to_link": "//horariodebuses.com/cr/busstop.php?city=San%20Jose&lang=en&ruta=bu,t&comp=Transp%20S%20Carlos%20-%20S%20Jose&tele=2460-5032&cweb=&ort=Calle%2012%20Av%207-9&lon=-84.08383&lat=9.939262", "to_lon": "84.08383", "trans_name": "Transp S Carlos - S José", "trans_tel": "2460-5032"}, {"date_arr": "Mo, 12/23", "date_dep": "Mo, 12/23", "from": "San Antonio de Monterrey", "from_link": "//horariodebuses.com/cr/busstop.php?city=San%20Antonio%20de%20Monterrey&lang=en&ruta=bu,f&comp=Transp%20S%20Carlos%20-%20S%20Jose&tele=2460-5032&cweb=&ort=&lon=0&lat=0", "remarks": " Journey duration: 4:15h Bus:  comes   from Guatuso ", "time_arr": "20:00", "time_dep": "15:45", "to": "San José", "to_lat": "9.939262", "to_link": "//horariodebuses.com/cr/busstop.php?city=San%20Jose&lang=en&ruta=bu,t&comp=Transp%20S%20Carlos%20-%20S%20Jose&tele=2460-5032&cweb=&ort=Calle%2012%20Av%207-9&lon=-84.08383&lat=9.939262", "to_lon": "84.08383", "trans_name": "Transp S Carlos - S José", "trans_tel": "2460-5032"}], "saturday": [{"date_arr": "Sa, 12/28", "date_dep": "Sa, 12/28", "from": "San Antonio de Monterrey", "from_link": "//horariodebuses.com/cr/busstop.php?city=San%20Antonio%20de%20Monterrey&lang=en&ruta=bu,f&comp=Transp%20S%20Carlos%20-%20S%20Jose&tele=2460-5032&cweb=&ort=&lon=0&lat=0", "remarks": " Journey duration: 4:15h Bus:  comes   from Guatuso ", "time_arr": "13:00", "time_dep": "08:45", "to": "San José", "to_lat": "9.939262", "to_link": "//horariodebuses.com/cr/busstop.php?city=San%20Jose&lang=en&ruta=bu,t&comp=Transp%20S%20Carlos%20-%20S%20Jose&tele=2460-5032&cweb=&ort=Calle%2012%20Av%207-9&lon=-84.08383&lat=9.939262", "to_lon": "84.08383", "trans_name": "Transp S Carlos - S José", "trans_tel": "2460-5032"}, {"date_arr": "Sa, 12/28", "date_dep": "Sa, 12/28", "from": "San Antonio de Monterrey", "from_link": "//horariodebuses.com/cr/busstop.php?city=San%20Antonio%20de%20Monterrey&lang=en&ruta=bu,f&comp=Transp%20S%20Carlos%20-%20S%20Jose&tele=2460-5032&cweb=&ort=&lon=0&lat=0", "remarks": " Journey duration: 4:15h Bus:  comes   from Guatuso ", "time_arr": "16:30", "time_dep": "12:15", "to": "San José", "to_lat": "9.939262", "to_link": "//horariodebuses.com/cr/busstop.php?city=San%20Jose&lang=en&ruta=bu,t&comp=Transp%20S%20Carlos%20-%20S%20Jose&tele=2460-5032&cweb=&ort=Calle%2012%20Av%207-9&lon=-84.08383&lat=9.939262", "to_lon": "84.08383", "trans_name": "Transp S Carlos - S José", "trans_tel": "2460-5032"}, {"date_arr": "Sa, 12/28", "date_dep": "Sa, 12/28", "from": "San Antonio de Monterrey", "from_link": "//horariodebuses.com/cr/busstop.php?city=San%20Antonio%20de%20Monterrey&lang=en&ruta=bu,f&comp=Transp%20S%20Carlos%20-%20S%20Jose&tele=2460-5032&cweb=&ort=&lon=0&lat=0", "remarks": " Journey duration: 4:15h Bus:  comes   from Guatuso ", "time_arr": "20:00", "time_dep": "15:45", "to": "San José", "to_lat": "9.939262", "to_link": "//horariodebuses.com/cr/busstop.php?city=San%20Jose&lang=en&ruta=bu,t&comp=Transp%20S%20Carlos%20-%20S%20Jose&tele=2460-5032&cweb=&ort=Calle%2012%20Av%207-9&lon=-84.08383&lat=9.939262", "to_lon": "84.08383", "trans_name": "Transp S Carlos - S José", "trans_tel": "2460-5032"}], "sunday": [{"date_arr": "Su, 12/29", "date_dep": "Su, 12/29", "from": "San Antonio de Monterrey", "from_link": "//horariodebuses.com/cr/busstop.php?city=San%20Antonio%20de%20Monterrey&lang=en&ruta=bu,f&comp=Transp%20S%20Carlos%20-%20S%20Jose&tele=2460-5032&cweb=&ort=&lon=0&lat=0", "remarks": " Journey duration: 4:15h Bus:  comes   from Guatuso ", "time_arr": "13:00", "time_dep": "08:45", "to": "San José", "to_lat": "9.939262", "to_link": "//horariodebuses.com/cr/busstop.php?city=San%20Jose&lang=en&ruta=bu,t&comp=Transp%20S%20Carlos%20-%20S%20Jose&tele=2460-5032&cweb=&ort=Calle%2012%20Av%207-9&lon=-84.08383&lat=9.939262", "to_lon": "84.08383", "trans_name": "Transp S Carlos - S José", "trans_tel": "2460-5032"}, {"date_arr": "Su, 12/29", "date_dep": "Su, 12/29", "from": "San Antonio de Monterrey", "from_link": "//horariodebuses.com/cr/busstop.php?city=San%20Antonio%20de%20Monterrey&lang=en&ruta=bu,f&comp=Transp%20S%20Carlos%20-%20S%20Jose&tele=2460-5032&cweb=&ort=&lon=0&lat=0", "remarks": " Journey duration: 4:15h Bus:  comes   from Guatuso ", "time_arr": "16:30", "time_dep": "12:15", "to": "San José", "to_lat": "9.939262", "to_link": "//horariodebuses.com/cr/busstop.php?city=San%20Jose&lang=en&ruta=bu,t&comp=Transp%20S%20Carlos%20-%20S%20Jose&tele=2460-5032&cweb=&ort=Calle%2012%20Av%207-9&lon=-84.08383&lat=9.939262", "to_lon": "84.08383", "trans_name": "Transp S Carlos - S José", "trans_tel": "2460-5032"}, {"date_arr": "Su, 12/29", "date_dep": "Su, 12/29", "from": "San Antonio de Monterrey", "from_link": "//horariodebuses.com/cr/busstop.php?city=San%20Antonio%20de%20Monterrey&lang=en&ruta=bu,f&comp=Transp%20S%20Carlos%20-%20S%20Jose&tele=2460-5032&cweb=&ort=&lon=0&lat=0", "remarks": " Journey duration: 4:15h Bus:  comes   from Guatuso ", "time_arr": "20:00", "time_dep": "15:45", "to": "San José", "to_lat": "9.939262", "to_link": "//horariodebuses.com/cr/busstop.php?city=San%20Jose&lang=en&ruta=bu,t&comp=Transp%20S%20Carlos%20-%20S%20Jose&tele=2460-5032&cweb=&ort=Calle%2012%20Av%207-9&lon=-84.08383&lat=9.939262", "to_lon": "84.08383", "trans_name": "Transp S Carlos - S José", "trans_tel": "2460-5032"}], "thursday": [{"date_arr": "Th, 12/26", "date_dep": "Th, 12/26", "from": "San Antonio de Monterrey", "from_link": "//horariodebuses.com/cr/busstop.php?city=San%20Antonio%20de%20Monterrey&lang=en&ruta=bu,f&comp=Transp%20S%20Carlos%20-%20S%20Jose&tele=2460-5032&cweb=&ort=&lon=0&lat=0", "remarks": " Journey duration: 4:15h Bus:  comes   from Guatuso ", "time_arr": "13:00", "time_dep": "08:45", "to": "San José", "to_lat": "9.939262", "to_link": "//horariodebuses.com/cr/busstop.php?city=San%20Jose&lang=en&ruta=bu,t&comp=Transp%20S%20Carlos%20-%20S%20Jose&tele=2460-5032&cweb=&ort=Calle%2012%20Av%207-9&lon=-84.08383&lat=9.939262", "to_lon": "84.08383", "trans_name": "Transp S Carlos - S José", "trans_tel": "2460-5032"}, {"date_arr": "Th, 12/26", "date_dep": "Th, 12/26", "from": "San Antonio de Monterrey", "from_link": "//horariodebuses.com/cr/busstop.php?city=San%20Antonio%20de%20Monterrey&lang=en&ruta=bu,f&comp=Transnorte%20de%20Upala&tele=2470-0743&cweb=www.transnortecr.com&ort=&lon=0&lat=0", "remarks": " Journey duration: 4:15h Bus:  comes   from Upala ", "time_arr": "15:00", "time_dep": "10:45", "to": "San José", "to_lat": "9.93882880034025", "to_link": "//horariodebuses.com/cr/busstop.php?city=San%20Jose&lang=en&ruta=bu,t&comp=Transnorte%20de%20Upala&tele=2470-0743&cweb=www.transnortecr.com&ort=Calle%2012,%20Av%207-9&lon=-84.0838730335236&lat=9.93882880034025", "to_lon": "84.0838730335236", "trans_link": "//www.transnortecr.com", "trans_name": "Transnorte de Upala", "trans_tel": "2470-0743"}, {"date_arr": "Th, 12/26", "date_dep": "Th, 12/26", "from": "San Antonio de Monterrey", "from_link": "//horariodebuses.com/cr/busstop.php?city=San%20Antonio%20de%20Monterrey&lang=en&ruta=bu,f&comp=Transp%20S%20Carlos%20-%20S%20Jose&tele=2460-5032&cweb=&ort=&lon=0&lat=0", "remarks": " Journey duration: 4:15h Bus:  comes   from Guatuso ", "time_arr": "16:30", "time_dep": "12:15", "to": "San José", "to_lat": "9.939262", "to_link": "//horariodebuses.com/cr/busstop.php?city=San%20Jose&lang=en&ruta=bu,t&comp=Transp%20S%20Carlos%20-%20S%20Jose&tele=2460-5032&cweb=&ort=Calle%2012%20Av%207-9&lon=-84.08383&lat=9.939262", "to_lon": "84.08383", "trans_name": "Transp S Carlos - S José", "trans_tel": "2460-5032"}, {"date_arr": "Th, 12/26", "date_dep": "Th, 12/26", "from": "San Antonio de Monterrey", "from_link": "//horariodebuses.com/cr/busstop.php?city=San%20Antonio%20de%20Monterrey&lang=en&ruta=bu,f&comp=Transp%20S%20Carlos%20-%20S%20Jose&tele=2460-5032&cweb=&ort=&lon=0&lat=0", "remarks": " Journey duration: 4:15h Bus:  comes   from Guatuso ", "time_arr": "20:00", "time_dep": "15:45", "to": "San José", "to_lat": "9.939262", "to_link": "//horariodebuses.com/cr/busstop.php?city=San%20Jose&lang=en&ruta=bu,t&comp=Transp%20S%20Carlos%20-%20S%20Jose&tele=2460-5032&cweb=&ort=Calle%2012%20Av%207-9&lon=-84.08383&lat=9.939262", "to_lon": "84.08383", "trans_name": "Transp S Carlos - S José", "trans_tel": "2460-5032"}], "to": "San José", "tuesday": [{"date_arr": "Tu, 12/24", "date_dep": "Tu, 12/24", "from": "San Antonio de Monterrey", "from_link": "//horariodebuses.com/cr/busstop.php?city=San%20Antonio%20de%20Monterrey&lang=en&ruta=bu,f&comp=Transp%20S%20Carlos%20-%20S%20Jose&tele=2460-5032&cweb=&ort=&lon=0&lat=0", "remarks": " Journey duration: 4:15h Bus:  comes   from Guatuso ", "time_arr": "13:00", "time_dep": "08:45", "to": "San José", "to_lat": "9.939262", "to_link": "//horariodebuses.com/cr/busstop.php?city=San%20Jose&lang=en&ruta=bu,t&comp=Transp%20S%20Carlos%20-%20S%20Jose&tele=2460-5032&cweb=&ort=Calle%2012%20Av%207-9&lon=-84.08383&lat=9.939262", "to_lon": "84.08383", "trans_name": "Transp S Carlos - S José", "trans_tel": "2460-5032"}, {"date_arr": "Tu, 12/24", "date_dep": "Tu, 12/24", "from": "San Antonio de Monterrey", "from_link": "//horariodebuses.com/cr/busstop.php?city=San%20Antonio%20de%20Monterrey&lang=en&ruta=bu,f&comp=Transnorte%20de%20Upala&tele=2470-0743&cweb=www.transnortecr.com&ort=&lon=0&lat=0", "remarks": " Journey duration: 4:15h Bus:  comes   from Upala ", "time_arr": "15:00", "time_dep": "10:45", "to": "San José", "to_lat": "9.93882880034025", "to_link": "//horariodebuses.com/cr/busstop.php?city=San%20Jose&lang=en&ruta=bu,t&comp=Transnorte%20de%20Upala&tele=2470-0743&cweb=www.transnortecr.com&ort=Calle%2012,%20Av%207-9&lon=-84.0838730335236&lat=9.93882880034025", "to_lon": "84.0838730335236", "trans_link": "//www.transnortecr.com", "trans_name": "Transnorte de Upala", "trans_tel": "2470-0743"}, {"date_arr": "Tu, 12/24", "date_dep": "Tu, 12/24", "from": "San Antonio de Monterrey", "from_link": "//horariodebuses.com/cr/busstop.php?city=San%20Antonio%20de%20Monterrey&lang=en&ruta=bu,f&comp=Transp%20S%20Carlos%20-%20S%20Jose&tele=2460-5032&cweb=&ort=&lon=0&lat=0", "remarks": " Journey duration: 4:15h Bus:  comes   from Guatuso ", "time_arr": "16:30", "time_dep": "12:15", "to": "San José", "to_lat": "9.939262", "to_link": "//horariodebuses.com/cr/busstop.php?city=San%20Jose&lang=en&ruta=bu,t&comp=Transp%20S%20Carlos%20-%20S%20Jose&tele=2460-5032&cweb=&ort=Calle%2012%20Av%207-9&lon=-84.08383&lat=9.939262", "to_lon": "84.08383", "trans_name": "Transp S Carlos - S José", "trans_tel": "2460-5032"}, {"date_arr": "Tu, 12/24", "date_dep": "Tu, 12/24", "from": "San Antonio de Monterrey", "from_link": "//horariodebuses.com/cr/busstop.php?city=San%20Antonio%20de%20Monterrey&lang=en&ruta=bu,f&comp=Transp%20S%20Carlos%20-%20S%20Jose&tele=2460-5032&cweb=&ort=&lon=0&lat=0", "remarks": " Journey duration: 4:15h Bus:  comes   from Guatuso ", "time_arr": "20:00", "time_dep": "15:45", "to": "San José", "to_lat": "9.939262", "to_link": "//horariodebuses.com/cr/busstop.php?city=San%20Jose&lang=en&ruta=bu,t&comp=Transp%20S%20Carlos%20-%20S%20Jose&tele=2460-5032&cweb=&ort=Calle%2012%20Av%207-9&lon=-84.08383&lat=9.939262", "to_lon": "84.08383", "trans_name": "Transp S Carlos - S José", "trans_tel": "2460-5032"}], "wednesday": [{"date_arr": "We, 12/25", "date_dep": "We, 12/25", "from": "San Antonio de Monterrey", "from_link": "//horariodebuses.com/cr/busstop.php?city=San%20Antonio%20de%20Monterrey&lang=en&ruta=bu,f&comp=Transp%20S%20Carlos%20-%20S%20Jose&tele=2460-5032&cweb=&ort=&lon=0&lat=0", "remarks": " Journey duration: 4:15h Bus:  comes   from Guatuso ", "time_arr": "13:00", "time_dep": "08:45", "to": "San José", "to_lat": "9.939262", "to_link": "//horariodebuses.com/cr/busstop.php?city=San%20Jose&lang=en&ruta=bu,t&comp=Transp%20S%20Carlos%20-%20S%20Jose&tele=2460-5032&cweb=&ort=Calle%2012%20Av%207-9&lon=-84.08383&lat=9.939262", "to_lon": "84.08383", "trans_name": "Transp S Carlos - S José", "trans_tel": "2460-5032"}, {"date_arr": "We, 12/25", "date_dep": "We, 12/25", "from": "San Antonio de Monterrey", "from_link": "//horariodebuses.com/cr/busstop.php?city=San%20Antonio%20de%20Monterrey&lang=en&ruta=bu,f&comp=Transnorte%20de%20Upala&tele=2470-0743&cweb=www.transnortecr.com&ort=&lon=0&lat=0", "remarks": " Journey duration: 4:15h Bus:  comes   from Upala ", "time_arr": "15:00", "time_dep": "10:45", "to": "San José", "to_lat": "9.93882880034025", "to_link": "//horariodebuses.com/cr/busstop.php?city=San%20Jose&lang=en&ruta=bu,t&comp=Transnorte%20de%20Upala&tele=2470-0743&cweb=www.transnortecr.com&ort=Calle%2012,%20Av%207-9&lon=-84.0838730335236&lat=9.93882880034025", "to_lon": "84.0838730335236", "trans_link": "//www.transnortecr.com", "trans_name": "Transnorte de Upala", "trans_tel": "2470-0743"}, {"date_arr": "We, 12/25", "date_dep": "We, 12/25", "from": "San Antonio de Monterrey", "from_link": "//horariodebuses.com/cr/busstop.php?city=San%20Antonio%20de%20Monterrey&lang=en&ruta=bu,f&comp=Transp%20S%20Carlos%20-%20S%20Jose&tele=2460-5032&cweb=&ort=&lon=0&lat=0", "remarks": " Journey duration: 4:15h Bus:  comes   from Guatuso ", "time_arr": "16:30", "time_dep": "12:15", "to": "San José", "to_lat": "9.939262", "to_link": "//horariodebuses.com/cr/busstop.php?city=San%20Jose&lang=en&ruta=bu,t&comp=Transp%20S%20Carlos%20-%20S%20Jose&tele=2460-5032&cweb=&ort=Calle%2012%20Av%207-9&lon=-84.08383&lat=9.939262", "to_lon": "84.08383", "trans_name": "Transp S Carlos - S José", "trans_tel": "2460-5032"}, {"date_arr": "We, 12/25", "date_dep": "We, 12/25", "from": "San Antonio de Monterrey", "from_link": "//horariodebuses.com/cr/busstop.php?city=San%20Antonio%20de%20Monterrey&lang=en&ruta=bu,f&comp=Transp%20S%20Carlos%20-%20S%20Jose&tele=2460-5032&cweb=&ort=&lon=0&lat=0", "remarks": " Journey duration: 4:15h Bus:  comes   from Guatuso ", "time_arr": "20:00", "time_dep": "15:45", "to": "San José", "to_lat": "9.939262", "to_link": "//horariodebuses.com/cr/busstop.php?city=San%20Jose&lang=en&ruta=bu,t&comp=Transp%20S%20Carlos%20-%20S%20Jose&tele=2460-5032&cweb=&ort=Calle%2012%20Av%207-9&lon=-84.08383&lat=9.939262", "to_lon": "84.08383", "trans_name": "Transp S Carlos - S José", "trans_tel": "2460-5032"}]}