{"0.0": {"lat": 0.0, "lon": 0.0, "schedule": {"monday": [{"date_arr": "monday", "remarks": " Journey duration: 1:40h Bus:  comes from Playa Brasilito ", "time_arr": "04:45", "time_dep": "03:05", "trans_name": "Transp. La Pampa", "trans_tel": "2680-0392"}, {"date_arr": "monday", "remarks": " Journey duration: 1:40h Bus:  comes from Playa Brasilito ", "time_arr": "11:00", "time_dep": "09:20", "trans_name": "Transp. La Pampa", "trans_tel": "2680-0392"}, {"date_arr": "monday", "remarks": " Journey duration: 1:40h Bus:  comes from Playa Brasilito ", "time_arr": "16:00", "time_dep": "14:20", "trans_name": "Transp. La Pampa", "trans_tel": "2680-0392"}], "tuesday": [{"date_arr": "tuesday", "remarks": " Journey duration: 1:40h Bus:  comes from Playa Brasilito ", "time_arr": "04:45", "time_dep": "03:05", "trans_name": "Transp. La Pampa", "trans_tel": "2680-0392"}, {"date_arr": "tuesday", "remarks": " Journey duration: 1:40h Bus:  comes from Playa Brasilito ", "time_arr": "11:00", "time_dep": "09:20", "trans_name": "Transp. La Pampa", "trans_tel": "2680-0392"}]}}}