{"94.54716894486401": {"lat": 10.076403354196286, "lon": 84.47076559066772, "schedule": {"monday": [{"date_arr": "monday", "remarks": " Journey duration: 1:00h Bus: indirecto ", "time_arr": "06:20", "time_dep": "05:20", "to_lat": "9.975993722371648", "to_lon": "84.83028888702393", "trans_name": "Empresarios Unidos", "trans_tel": "2222-8231"}, {"date_arr": "monday", "remarks": " Journey duration: 0:50h Bus:  continues to Santa Teresa ", "time_arr": "08:15", "time_dep": "07:25", "to_lat": "9.978117606187336", "to_lon": "84.84860301017761", "trans_link": "//www.transportescobanocr.com", "trans_name": "Transportes Cobano", "trans_tel": "8389-7177"}, {"date_arr": "monday", "remarks": " Journey duration: 1:00h Bus: indirecto ", "time_arr": "08:35", "time_dep": "07:35", "to_lat": "9.975993722371648", "to_lon": "84.83028888702393", "trans_name": "Empresarios Unidos", "trans_tel": "2222-8231"}, {"date_arr": "monday", "remarks": " Journey duration: 1:00h Bus: indirecto ", "time_arr": "09:35", "time_dep": "08:35", "to_lat": "9.975993722371648", "to_lon": "84.83028888702393", "trans_name": "Empresarios Unidos", "trans_tel": "2222-8231"}, {"date_arr": "monday", "remarks": " Journey duration: 1:00h Bus: indirecto ", "time_arr": "10:35", "time_dep": "09:35", "to_lat": "9.975993722371648", "to_lon": "84.83028888702393", "trans_name": "Empresarios Unidos", "trans_tel": "2222-8231"}, {"date_arr": "monday", "remarks": " Journey duration: 1:00h Bus: indirecto ", "time_arr": "11:35", "time_dep": "10:35", "to_lat": "9.975993722371648", "to_lon": "84.83028888702393", "trans_name": "Empresarios Unidos", "trans_tel": "2222-8231"}, {"date_arr": "monday", "remarks": " Journey duration: 1:00h Bus: indirecto ", "time_arr": "12:35", "time_dep": "11:35", "to_lat": "9.975993722371648", "to_lon": "84.83028888702393", "trans_name": "Empresarios Unidos", "trans_tel": "2222-8231"}]}}, "94.5608075145199": {"lat": 10.0889153960659, "lon": 84.471892118454, "schedule": {"monday": [{"date_arr": "monday", "remarks": " Journey duration: 1:00h Bus ", "time_arr": "06:00", "time_dep": "05:00", "to_lat": "9.97599372237165", "to_lon": "84.8302888870239", "trans_name": "Empresarios Unidos", "trans_tel": "2445-7225"}, {"date_arr": "monday", "remarks": " Journey duration: 1:00h Bus ", "time_arr": "07:00", "time_dep": "06:00", "to_lat": "9.97599372237165", "to_lon": "84.8302888870239", "trans_name": "Empresarios Unidos", "trans_tel": "2445-7225"}, {"date_arr": "monday", "remarks": " Journey duration: 1:00h Bus ", "time_arr": "08:00", "time_dep": "07:00", "to_lat": "9.97599372237165", "to_lon": "84.8302888870239", "trans_name": "Empresarios Unidos", "trans_tel": "2445-7225"}, {"date_arr": "monday", "remarks": " Journey duration: 1:00h Bus ", "time_arr": "09:00", "time_dep": "08:00", "to_lat": "9.97599372237165", "to_lon": "84.8302888870239", "trans_name": "Empresarios Unidos", "trans_tel": "2445-7225"}, {"date_arr": "monday", "remarks": " Journey duration: 1:00h Bus ", "time_arr": "10:00", "time_dep": "09:00", "to_lat": "9.97599372237165", "to_lon": "84.8302888870239", "trans_name": "Empresarios Unidos", "trans_tel": "2445-7225"}, {"date_arr": "monday", "remarks": " Journey duration: 1:00h Bus ", "time_arr": "11:00", "time_dep": "10:00", "to_lat": "9.97599372237165", "to_lon": "84.8302888870239", "trans_name": "Empresarios Unidos", "trans_tel": "2445-7225"}, {"date_arr": "monday", "remarks": " Journey duration: 1:00h Bus ", "time_arr": "12:00", "time_dep": "11:00", "to_lat": "9.97599372237165", "to_lon": "84.8302888870239", "trans_name": "Empresarios Unidos", "trans_tel": "2445-7225"}]}}}