{"from": "San José", "monday": [{"date_arr": "Mo, 12/23", "date_dep": "Mo, 12/23", "from": "San José", "from_lat": "9.939262", "from_link": "//horariodebuses.com/cr/busstop.php?city=San%20Jose&lang=en&ruta=bu,f&comp=Transp%20S%20Carlos%20-%20S%20Jose&tele=2256-8914&cweb=&ort=Calle%2012%20Av%207-9&lon=-84.08383&lat=9.939262", "from_lon": "84.08383", "remarks": " Journey duration: 3:30h Bus:  continues to Guatuso ", "time_arr": "08:30", "time_dep": "05:00", "to": "El Muelle de San Carlos", "to_link": "//horariodebuses.com/cr/busstop.php?city=El%20Muelle%20de%20San%20Carlos&lang=en&ruta=bu,t&comp=Transp%20S%20Carlos%20-%20S%20Jose&tele=2256-8914&cweb=&ort=&lon=0&lat=0", "trans_name": "Transp S Carlos - S José", "trans_tel": "2256-8914"}, {"date_arr": "Mo, 12/23", "date_dep": "Mo, 12/23", "from": "San José", "from_lat": "9.939262", "from_link": "//horariodebuses.com/cr/busstop.php?city=San%20Jose&lang=en&ruta=bu,f&comp=Transp%20S%20Carlos%20-%20S%20Jose&tele=2255-4300&cweb=&ort=Calle%2012%20Ave.%207-9&lon=-84.08383&lat=9.939262", "from_lon": "84.08383", "remarks": " Journey duration: 3:30h Bus:  continues to La Fortuna ", "time_arr": "09:45", "time_dep": "06:15", "to": "El Muelle de San Carlos", "to_link": "//horariodebuses.com/cr/busstop.php?city=El%20Muelle%20de%20San%20Carlos&lang=en&ruta=bu,t&comp=Transp%20S%20Carlos%20-%20S%20Jose&tele=2255-4300&cweb=&ort=&lon=0&lat=0", "trans_name": "Transp S Carlos - S José", "trans_tel": "2255-4300"}, {"date_arr": "Mo, 12/23", "date_dep": "Mo, 12/23", "from": "San José", "from_lat": "9.939262", "from_link": "//horariodebuses.com/cr/busstop.php?city=San%20Jose&lang=en&ruta=bu,f&comp=Transp%20S%20Carlos%20-%20S%20Jose&tele=2255-4300&cweb=&ort=Calle%2012%20Ave.%207-9&lon=-84.08383&lat=9.939262", "from_lon": "84.08383", "remarks": " Journey duration: 3:30h Bus:  continues to La Fortuna ", "time_arr": "12:10", "time_dep": "08:40", "to": "El Muelle de San Carlos", "to_link": "//horariodebuses.com/cr/busstop.php?city=El%20Muelle%20de%20San%20Carlos&lang=en&ruta=bu,t&comp=Transp%20S%20Carlos%20-%20S%20Jose&tele=2255-4300&cweb=&ort=&lon=0&lat=0", "trans_name": "Transp S Carlos - S José", "trans_tel": "2255-4300"}], "to": "El Muelle de San Carlos"}