{"from": "Rincón de Osa", "monday": [{"date_arr": "Mo, 12/23", "date_dep": "Mo, 12/23", "from": "Rincón de Osa", "from_link": "//horariodebuses.com/cr/busstop.php?city=Rincon%20de%20Osa&lang=en&ruta=bu,f&comp=Transp.%20Blanco&tele=2735-5189&cweb=&ort=&lon=0&lat=0", "remarks": " Journey duration: 4:25h Bus:  comes from Puerto Jiménez ", "time_arr": "10:35", "time_dep": "06:10", "to": "Nivel", "to_link": "//horariodebuses.com/cr/busstop.php?city=Nivel&lang=en&ruta=bu,t&comp=Transp.%20Blanco&tele=2735-5189&cweb=&ort=&lon=0&lat=0", "trans_name": "Transp. Blanco", "trans_tel": "2735-5189"}, {"date_arr": "Mo, 12/23", "date_dep": "Mo, 12/23", "from": "Rincón de Osa", "from_link": "//horariodebuses.com/cr/busstop.php?city=Rincon%20de%20Osa&lang=en&ruta=bu,f&comp=Transp.%20Blanco&tele=2735-5189&cweb=&ort=&lon=0&lat=0", "remarks": " Journey duration: 4:25h Bus:  comes from Puerto Jiménez ", "time_arr": "14:35", "time_dep": "10:10", "to": "Nivel", "to_link": "//horariodebuses.com/cr/busstop.php?city=Nivel&lang=en&ruta=bu,t&comp=Transp.%20Blanco&tele=2735-5189&cweb=&ort=&lon=0&lat=0", "trans_name": "Transp. Blanco", "trans_tel": "2735-5189"}], "to": "Nivel", "tuesday": [{"date_arr": "Tu, 12/24", "date_dep": "Tu, 12/24", "from": "Rincón de Osa", "from_link": "//horariodebuses.com/cr/busstop.php?city=Rincon%20de%20Osa&lang=en&ruta=bu,f&comp=Transp.%20Blanco&tele=2735-5189&cweb=&ort=&lon=0&lat=0", "remarks": " Journey duration: 4:25h Bus:  comes from Puerto Jiménez ", "time_arr": "10:35", "time_dep": "06:10", "to": "Nivel", "to_link": "//horariodebuses.com/cr/busstop.php?city=Nivel&lang=en&ruta=bu,t&comp=Transp.%20Blanco&tele=2735-5189&cweb=&ort=&lon=0&lat=0", "trans_name": "Transp. Blanco", "trans_tel": "2735-5189"}, {"date_arr": "Tu, 12/24", "date_dep": "Tu, 12/24", "from": "Rincón de Osa", "from_link": "//horariodebuses.com/cr/busstop.php?city=Rincon%20de%20Osa&lang=en&ruta=bu,f&comp=Transp.%20Blanco&tele=2735-5189&cweb=&ort=&lon=0&lat=0", "remarks": " Journey duration: 4:25h Bus:  comes from Puerto Jiménez ", "time_arr": "14:35", "time_dep": "10:10", "to": "Nivel", "to_link": "//horariodebuses.com/cr/busstop.php?city=Nivel&lang=en&ruta=bu,t&comp=Transp.%20Blanco&tele=2735-5189&cweb=&ort=&lon=0&lat=0", "trans_name": "Transp. Blanco", "trans_tel": "2735-5189"}], "wednesday": [{"date_arr": "We, 12/25", "date_dep": "We, 12/25", "from": "Rincón de Osa", "from_link": "//horariodebuses.com/cr/busstop.php?city=Rincon%20de%20Osa&lang=en&ruta=bu,f&comp=Transp.%20Blanco&tele=2735-5189&cweb=&ort=&lon=0&lat=0", "remarks": " Journey duration: 4:25h Bus:  comes from Puerto Jiménez ", "time_arr": "10:35", "time_dep": "06:10", "to": "Nivel", "to_link": "//horariodebuses.com/cr/busstop.php?city=Nivel&lang=en&ruta=bu,t&comp=Transp.%20Blanco&tele=2735-5189&cweb=&ort=&lon=0&lat=0", "trans_name": "Transp. Blanco", "trans_tel": "2735-5189"}, {"date_arr": "We, 12/25", "date_dep": "We, 12/25", "from": "Rincón de Osa", "from_link": "//horariodebuses.com/cr/busstop.php?city=Rincon%20de%20Osa&lang=en&ruta=bu,f&comp=Transp.%20Blanco&tele=2735-5189&cweb=&ort=&lon=0&lat=0", "remarks": " Journey duration: 4:25h Bus:  comes from Puerto Jiménez ", "time_arr": "14:35", "time_dep": "10:10", "to": "Nivel", "to_link": "//horariodebuses.com/cr/busstop.php?city=Nivel&lang=en&ruta=bu,t&comp=Transp.%20Blanco&tele=2735-5189&cweb=&ort=&lon=0&lat=0", "trans_name": "Transp. Blanco", "trans_tel": "2735-5189"}]}