{"-74.507397": {"lat": 10.31551, "lon": -84.822907, "schedule": {"friday": [{"date_arr": "friday", "remarks": " Journey duration: 3:00h Bus ", "time_arr": "07:30", "time_dep": "04:30", "trans_name": "Luis Angel Vargas"}, {"date_arr": "friday", "remarks": " Journey duration: 3:00h Bus ", "time_arr": "08:30", "time_dep": "05:30", "to_lat": "9.97601485561216", "to_lon": "84.8287010192871", "trans_name": "Transmonteverde S.A.", "trans_tel": "2645-5159"}, {"date_arr": "friday", "remarks": " Journey duration: 3:00h Bus ", "time_arr": "09:00", "time_dep": "06:00", "to_lat": "9.97601485561216", "to_lon": "84.8287010192871", "trans_name": "Transmonteverde S.A.", "trans_tel": "2645-5159"}, {"date_arr": "friday", "remarks": " Journey duration: 3:00h Bus ", "time_arr": "18:00", "time_dep": "15:00", "to_lat": "9.97601485561216", "to_lon": "84.8287010192871", "trans_name": "Transmonteverde S.A.", "trans_tel": "2645-5159"}], "monday": [{"date_arr": "monday", "remarks": " Journey duration: 3:00h Bus ", "time_arr": "07:30", "time_dep": "04:30", "trans_name": "Luis Angel Vargas"}, {"date_arr": "monday", "remarks": " Journey duration: 3:00h Bus ", "time_arr": "08:30", "time_dep": "05:30", "to_lat": "9.97601485561216", "to_lon": "84.8287010192871", "trans_name": "Transmonteverde S.A.", "trans_tel": "2645-5159"}, {"date_arr": "monday", "remarks": " Journey duration: 3:00h Bus ", "time_arr": "09:00", "time_dep": "06:00", "to_lat": "9.97601485561216", "to_lon": "84.8287010192871", "trans_name": "Transmonteverde S.A.", "trans_tel": "2645-5159"}, {"date_arr": "monday", "remarks": " Journey duration: 3:00h Bus ", "time_arr": "18:00", "time_dep": "15:00", "to_lat": "9.97601485561216", "to_lon": "84.8287010192871", "trans_name": "Transmonteverde S.A.", "trans_tel": "2645-5159"}], "saturday": [{"date_arr": "saturday", "remarks": " Journey duration: 3:00h Bus ", "time_arr": "07:30", "time_dep": "04:30", "trans_name": "Luis Angel Vargas"}, {"date_arr": "saturday", "remarks": " Journey duration: 3:00h Bus ", "time_arr": "08:30", "time_dep": "05:30", "to_lat": "9.97601485561216", "to_lon": "84.8287010192871", "trans_name": "Transmonteverde S.A.", "trans_tel": "2645-5159"}, {"date_arr": "saturday", "remarks": " Journey duration: 3:00h Bus ", "time_arr": "09:00", "time_dep": "06:00", "to_lat": "9.97601485561216", "to_lon": "84.8287010192871", "trans_name": "Transmonteverde S.A.", "trans_tel": "2645-5159"}, {"date_arr": "saturday", "remarks": " Journey duration: 3:00h Bus ", "time_arr": "18:00", "time_dep": "15:00", "to_lat": "9.97601485561216", "to_lon": "84.8287010192871", "trans_name": "Transmonteverde S.A.", "trans_tel": "2645-5159"}], "sunday": [{"date_arr": "sunday", "remarks": " Journey duration: 3:00h Bus ", "time_arr": "07:30", "time_dep": "04:30", "trans_name": "Luis Angel Vargas"}, {"date_arr": "sunday", "remarks": " Journey duration: 3:00h Bus ", "time_arr": "08:30", "time_dep": "05:30", "to_lat": "9.97601485561216", "to_lon": "84.8287010192871", "trans_name": "Transmonteverde S.A.", "trans_tel": "2645-5159"}, {"date_arr": "sunday", "remarks": " Journey duration: 3:00h Bus ", "time_arr": "09:00", "time_dep": "06:00", "to_lat": "9.97601485561216", "to_lon": "84.8287010192871", "trans_name": "Transmonteverde S.A.", "trans_tel": "2645-5159"}, {"date_arr": "sunday", "remarks": " Journey duration: 3:00h Bus ", "time_arr": "18:00", "time_dep": "15:00", "to_lat": "9.97601485561216", "to_lon": "84.8287010192871", "trans_name": "Transmonteverde S.A.", "trans_tel": "2645-5159"}], "thursday": [{"date_arr": "thursday", "remarks": " Journey duration: 3:00h Bus ", "time_arr": "07:30", "time_dep": "04:30", "trans_name": "Luis Angel Vargas"}, {"date_arr": "thursday", "remarks": " Journey duration: 3:00h Bus ", "time_arr": "08:30", "time_dep": "05:30", "to_lat": "9.97601485561216", "to_lon": "84.8287010192871", "trans_name": "Transmonteverde S.A.", "trans_tel": "2645-5159"}, {"date_arr": "thursday", "remarks": " Journey duration: 3:00h Bus ", "time_arr": "09:00", "time_dep": "06:00", "to_lat": "9.97601485561216", "to_lon": "84.8287010192871", "trans_name": "Transmonteverde S.A.", "trans_tel": "2645-5159"}, {"date_arr": "thursday", "remarks": " Journey duration: 3:00h Bus ", "time_arr": "18:00", "time_dep": "15:00", "to_lat": "9.97601485561216", "to_lon": "84.8287010192871", "trans_name": "Transmonteverde S.A.", "trans_tel": "2645-5159"}], "tuesday": [{"date_arr": "tuesday", "remarks": " Journey duration: 3:00h Bus ", "time_arr": "07:30", "time_dep": "04:30", "trans_name": "Luis Angel Vargas"}, {"date_arr": "tuesday", "remarks": " Journey duration: 3:00h Bus ", "time_arr": "08:30", "time_dep": "05:30", "to_lat": "9.97601485561216", "to_lon": "84.8287010192871", "trans_name": "Transmonteverde S.A.", "trans_tel": "2645-5159"}, {"date_arr": "tuesday", "remarks": " Journey duration: 3:00h Bus ", "time_arr": "09:00", "time_dep": "06:00", "to_lat": "9.97601485561216", "to_lon": "84.8287010192871", "trans_name": "Transmonteverde S.A.", "trans_tel": "2645-5159"}, {"date_arr": "tuesday", "remarks": " Journey duration: 3:00h Bus ", "time_arr": "18:00", "time_dep": "15:00", "to_lat": "9.97601485561216", "to_lon": "84.8287010192871", "trans_name": "Transmonteverde S.A.", "trans_tel": "2645-5159"}], "wednesday": [{"date_arr": "wednesday", "remarks": " Journey duration: 3:00h Bus ", "time_arr": "07:30", "time_dep": "04:30", "trans_name": "Luis Angel Vargas"}, {"date_arr": "wednesday", "remarks": " Journey duration: 3:00h Bus ", "time_arr": "08:30", "time_dep": "05:30", "to_lat": "9.97601485561216", "to_lon": "84.8287010192871", "trans_name": "Transmonteverde S.A.", "trans_tel": "2645-5159"}, {"date_arr": "wednesday", "remarks": " Journey duration: 3:00h Bus ", "time_arr": "09:00", "time_dep": "06:00", "to_lat": "9.97601485561216", "to_lon": "84.8287010192871", "trans_name": "Transmonteverde S.A.", "trans_tel": "2645-5159"}, {"date_arr": "wednesday", "remarks": " Journey duration: 3:00h Bus ", "time_arr": "18:00", "time_dep": "15:00", "to_lat": "9.97601485561216", "to_lon": "84.8287010192871", "trans_name": "Transmonteverde S.A.", "trans_tel": "2645-5159"}]}}}