{"0.0": {"lat": 0.0, "lon": 0.0, "schedule": {"monday": [{"date_arr": "monday", "remarks": " Journey duration: 1:00h Bus ", "time_arr": "07:35", "time_dep": "06:35", "trans_link": "//www.transtusacr.com", "trans_name": "Transtusa", "trans_tel": "2557-5050"}, {"date_arr": "monday", "remarks": " Journey duration: 1:00h Bus ", "time_arr": "08:20", "time_dep": "07:20", "trans_link": "//www.transtusacr.com", "trans_name": "Transtusa", "trans_tel": "2557-5050"}, {"date_arr": "monday", "remarks": " Journey duration: 1:00h Bus ", "time_arr": "09:05", "time_dep": "08:05", "trans_link": "//www.transtusacr.com", "trans_name": "Transtusa", "trans_tel": "2557-5050"}, {"date_arr": "monday", "remarks": " Journey duration: 1:00h Bus ", "time_arr": "09:50", "time_dep": "08:50", "trans_link": "//www.transtusacr.com", "trans_name": "Transtusa", "trans_tel": "2557-5050"}, {"date_arr": "monday", "remarks": " Journey duration: 0:55h Bus: expresso ", "time_arr": "10:00", "time_dep": "09:05", "trans_link": "//www.transtusacr.com", "trans_name": "Transtusa", "trans_tel": "2557-5050"}, {"date_arr": "monday", "remarks": " Journey duration: 1:00h Bus ", "time_arr": "10:50", "time_dep": "09:50", "trans_link": "//www.transtusacr.com", "trans_name": "Transtusa", "trans_tel": "2557-5050"}, {"date_arr": "monday", "remarks": " Journey duration: 0:55h Bus: expresso ", "time_arr": "11:00", "time_dep": "10:05", "trans_link": "//www.transtusacr.com", "trans_name": "Transtusa", "trans_tel": "2557-5050"}, {"date_arr": "monday", "remarks": " Journey duration: 1:00h Bus ", "time_arr": "11:35", "time_dep": "10:35", "trans_link": "//www.transtusacr.com", "trans_name": "Transtusa", "trans_tel": "2557-5050"}, {"date_arr": "monday", "remarks": " Journey duration: 0:55h Bus: expresso ", "time_arr": "12:00", "time_dep": "11:05", "trans_link": "//www.transtusacr.com", "trans_name": "Transtusa", "trans_tel": "2557-5050"}, {"date_arr": "monday", "remarks": " Journey duration: 1:00h Bus ", "time_arr": "12:20", "time_dep": "11:20", "trans_link": "//www.transtusacr.com", "trans_name": "Transtusa", "trans_tel": "2557-5050"}, {"date_arr": "monday", "remarks": " Journey duration: 0:55h Bus: expresso ", "time_arr": "13:00", "time_dep": "12:05", "trans_link": "//www.transtusacr.com", "trans_name": "Transtusa", "trans_tel": "2557-5050"}, {"date_arr": "monday", "remarks": " Journey duration: 1:00h Bus ", "time_arr": "13:05", "time_dep": "12:05", "trans_link": "//www.transtusacr.com", "trans_name": "Transtusa", "trans_tel": "2557-5050"}, {"date_arr": "monday", "remarks": " Journey duration: 1:00h Bus ", "time_arr": "13:50", "time_dep": "12:50", "trans_link": "//www.transtusacr.com", "trans_name": "Transtusa", "trans_tel": "2557-5050"}, {"date_arr": "monday", "remarks": " Journey duration: 0:55h Bus: expresso ", "time_arr": "14:00", "time_dep": "13:05", "trans_link": "//www.transtusacr.com", "trans_name": "Transtusa", "trans_tel": "2557-5050"}, {"date_arr": "monday", "remarks": " Journey duration: 1:00h Bus ", "time_arr": "14:35", "time_dep": "13:35", "trans_link": "//www.transtusacr.com", "trans_name": "Transtusa", "trans_tel": "2557-5050"}, {"date_arr": "monday", "remarks": " Journey duration: 0:55h Bus: expresso ", "time_arr": "15:00", "time_dep": "14:05", "trans_link": "//www.transtusacr.com", "trans_name": "Transtusa", "trans_tel": "2557-5050"}, {"date_arr": "monday", "remarks": " Journey duration: 1:00h Bus ", "time_arr": "15:20", "time_dep": "14:20", "trans_link": "//www.transtusacr.com", "trans_name": "Transtusa", "trans_tel": "2557-5050"}, {"date_arr": "monday", "remarks": " Journey duration: 0:55h Bus: expresso ", "time_arr": "16:00", "time_dep": "15:05", "trans_link": "//www.transtusacr.com", "trans_name": "Transtusa", "trans_tel": "2557-5050"}, {"date_arr": "monday", "remarks": " Journey duration: 1:00h Bus ", "time_arr": "16:05", "time_dep": "15:05", "trans_link": "//www.transtusacr.com", "trans_name": "Transtusa", "trans_tel": "2557-5050"}]}}}