{"-74.435979": {"lat": 10.656222, "lon": -85.092201, "schedule": {"friday": [{"date_arr": "friday", "remarks": " Journey duration: 0:45h Bus:  comes from Cañas ", "time_arr": "06:15", "time_dep": "05:30", "trans_name": "Autotransp. de Upala", "trans_tel": "2470-0197"}, {"date_arr": "friday", "remarks": " Journey duration: 0:45h Bus:  comes from Cañas ", "time_arr": "07:45", "time_dep": "07:00", "trans_name": "Autotransp. de Upala", "trans_tel": "2470-0197"}, {"date_arr": "friday", "remarks": " Journey duration: 0:45h Bus:  comes from Cañas ", "time_arr": "10:15", "time_dep": "09:30", "trans_name": "Autotransp. de Upala", "trans_tel": "2470-0197"}, {"date_arr": "friday", "remarks": " Journey duration: 0:45h Bus:  comes from Cañas ", "time_arr": "13:00", "time_dep": "12:15", "trans_name": "Autotransp. de Upala", "trans_tel": "2470-0197"}, {"date_arr": "friday", "remarks": " Journey duration: 0:45h Bus:  comes from Cañas ", "time_arr": "14:45", "time_dep": "14:00", "trans_name": "Autotransp. de Upala", "trans_tel": "2470-0197"}, {"date_arr": "friday", "remarks": " Journey duration: 0:50h Bus ", "time_arr": "15:15", "time_dep": "14:25", "trans_link": "//www.transnortecr.com", "trans_name": "Transnorte de Upala", "trans_tel": "2221-9022"}, {"date_arr": "friday", "remarks": " Journey duration: 0:45h Bus:  comes from Cañas ", "time_arr": "17:15", "time_dep": "16:30", "trans_name": "Autotransp. de Upala", "trans_tel": "2470-0197"}, {"date_arr": "friday", "remarks": " Journey duration: 0:45h Bus:  comes from Cañas ", "time_arr": "19:15", "time_dep": "18:30", "trans_name": "Autotransp. de Upala", "trans_tel": "2470-0197"}, {"date_arr": "friday", "remarks": " Journey duration: 0:50h Bus ", "time_arr": "20:00", "time_dep": "19:10", "trans_link": "//www.transnortecr.com", "trans_name": "Transnorte de Upala", "trans_tel": "2221-9022"}, {"date_arr": "friday", "remarks": " Journey duration: 0:50h Bus ", "time_arr": "22:10", "time_dep": "21:20", "trans_link": "//www.transnortecr.com", "trans_name": "Transnorte de Upala", "trans_tel": "2221-9022"}], "monday": [{"date_arr": "monday", "remarks": " Journey duration: 0:45h Bus:  comes from Cañas ", "time_arr": "06:15", "time_dep": "05:30", "trans_name": "Autotransp. de Upala", "trans_tel": "2470-0197"}, {"date_arr": "monday", "remarks": " Journey duration: 0:45h Bus:  comes from Cañas ", "time_arr": "07:45", "time_dep": "07:00", "trans_name": "Autotransp. de Upala", "trans_tel": "2470-0197"}, {"date_arr": "monday", "remarks": " Journey duration: 0:45h Bus:  comes from Cañas ", "time_arr": "10:15", "time_dep": "09:30", "trans_name": "Autotransp. de Upala", "trans_tel": "2470-0197"}, {"date_arr": "monday", "remarks": " Journey duration: 0:45h Bus:  comes from Cañas ", "time_arr": "13:00", "time_dep": "12:15", "trans_name": "Autotransp. de Upala", "trans_tel": "2470-0197"}, {"date_arr": "monday", "remarks": " Journey duration: 0:45h Bus:  comes from Cañas ", "time_arr": "14:45", "time_dep": "14:00", "trans_name": "Autotransp. de Upala", "trans_tel": "2470-0197"}, {"date_arr": "monday", "remarks": " Journey duration: 0:50h Bus ", "time_arr": "15:15", "time_dep": "14:25", "trans_link": "//www.transnortecr.com", "trans_name": "Transnorte de Upala", "trans_tel": "2221-9022"}, {"date_arr": "monday", "remarks": " Journey duration: 0:45h Bus:  comes from Cañas ", "time_arr": "17:15", "time_dep": "16:30", "trans_name": "Autotransp. de Upala", "trans_tel": "2470-0197"}, {"date_arr": "monday", "remarks": " Journey duration: 0:45h Bus:  comes from Cañas ", "time_arr": "19:15", "time_dep": "18:30", "trans_name": "Autotransp. de Upala", "trans_tel": "2470-0197"}, {"date_arr": "monday", "remarks": " Journey duration: 0:50h Bus ", "time_arr": "20:00", "time_dep": "19:10", "trans_link": "//www.transnortecr.com", "trans_name": "Transnorte de Upala", "trans_tel": "2221-9022"}, {"date_arr": "monday", "remarks": " Journey duration: 0:50h Bus ", "time_arr": "22:10", "time_dep": "21:20", "trans_link": "//www.transnortecr.com", "trans_name": "Transnorte de Upala", "trans_tel": "2221-9022"}], "saturday": [{"date_arr": "saturday", "remarks": " Journey duration: 0:45h Bus:  comes from Cañas ", "time_arr": "06:15", "time_dep": "05:30", "trans_name": "Autotransp. de Upala", "trans_tel": "2470-0197"}, {"date_arr": "saturday", "remarks": " Journey duration: 0:45h Bus:  comes from Cañas ", "time_arr": "07:45", "time_dep": "07:00", "trans_name": "Autotransp. de Upala", "trans_tel": "2470-0197"}, {"date_arr": "saturday", "remarks": " Journey duration: 0:45h Bus:  comes from Cañas ", "time_arr": "10:15", "time_dep": "09:30", "trans_name": "Autotransp. de Upala", "trans_tel": "2470-0197"}, {"date_arr": "saturday", "remarks": " Journey duration: 0:45h Bus:  comes from Cañas ", "time_arr": "13:00", "time_dep": "12:15", "trans_name": "Autotransp. de Upala", "trans_tel": "2470-0197"}, {"date_arr": "saturday", "remarks": " Journey duration: 0:45h Bus:  comes from Cañas ", "time_arr": "14:45", "time_dep": "14:00", "trans_name": "Autotransp. de Upala", "trans_tel": "2470-0197"}, {"date_arr": "saturday", "remarks": " Journey duration: 0:50h Bus ", "time_arr": "15:15", "time_dep": "14:25", "trans_link": "//www.transnortecr.com", "trans_name": "Transnorte de Upala", "trans_tel": "2221-9022"}, {"date_arr": "saturday", "remarks": " Journey duration: 0:45h Bus:  comes from Cañas ", "time_arr": "17:15", "time_dep": "16:30", "trans_name": "Autotransp. de Upala", "trans_tel": "2470-0197"}, {"date_arr": "saturday", "remarks": " Journey duration: 0:45h Bus:  comes from Cañas ", "time_arr": "19:15", "time_dep": "18:30", "trans_name": "Autotransp. de Upala", "trans_tel": "2470-0197"}, {"date_arr": "saturday", "remarks": " Journey duration: 0:50h Bus ", "time_arr": "20:00", "time_dep": "19:10", "trans_link": "//www.transnortecr.com", "trans_name": "Transnorte de Upala", "trans_tel": "2221-9022"}, {"date_arr": "saturday", "remarks": " Journey duration: 0:50h Bus ", "time_arr": "22:10", "time_dep": "21:20", "trans_link": "//www.transnortecr.com", "trans_name": "Transnorte de Upala", "trans_tel": "2221-9022"}], "sunday": [{"date_arr": "sunday", "remarks": " Journey duration: 0:45h Bus:  comes from Cañas ", "time_arr": "06:15", "time_dep": "05:30", "trans_name": "Autotransp. de Upala", "trans_tel": "2470-0197"}, {"date_arr": "sunday", "remarks": " Journey duration: 0:45h Bus:  comes from Cañas ", "time_arr": "07:45", "time_dep": "07:00", "trans_name": "Autotransp. de Upala", "trans_tel": "2470-0197"}, {"date_arr": "sunday", "remarks": " Journey duration: 0:45h Bus:  comes from Cañas ", "time_arr": "10:15", "time_dep": "09:30", "trans_name": "Autotransp. de Upala", "trans_tel": "2470-0197"}, {"date_arr": "sunday", "remarks": " Journey duration: 0:45h Bus:  comes from Cañas ", "time_arr": "13:00", "time_dep": "12:15", "trans_name": "Autotransp. de Upala", "trans_tel": "2470-0197"}, {"date_arr": "sunday", "remarks": " Journey duration: 0:45h Bus:  comes from Cañas ", "time_arr": "14:45", "time_dep": "14:00", "trans_name": "Autotransp. de Upala", "trans_tel": "2470-0197"}, {"date_arr": "sunday", "remarks": " Journey duration: 0:50h Bus ", "time_arr": "15:15", "time_dep": "14:25", "trans_link": "//www.transnortecr.com", "trans_name": "Transnorte de Upala", "trans_tel": "2221-9022"}, {"date_arr": "sunday", "remarks": " Journey duration: 0:45h Bus:  comes from Cañas ", "time_arr": "17:15", "time_dep": "16:30", "trans_name": "Autotransp. de Upala", "trans_tel": "2470-0197"}, {"date_arr": "sunday", "remarks": " Journey duration: 0:45h Bus:  comes from Cañas ", "time_arr": "19:15", "time_dep": "18:30", "trans_name": "Autotransp. de Upala", "trans_tel": "2470-0197"}, {"date_arr": "sunday", "remarks": " Journey duration: 0:50h Bus ", "time_arr": "20:00", "time_dep": "19:10", "trans_link": "//www.transnortecr.com", "trans_name": "Transnorte de Upala", "trans_tel": "2221-9022"}, {"date_arr": "sunday", "remarks": " Journey duration: 0:50h Bus ", "time_arr": "22:10", "time_dep": "21:20", "trans_link": "//www.transnortecr.com", "trans_name": "Transnorte de Upala", "trans_tel": "2221-9022"}], "thursday": [{"date_arr": "thursday", "remarks": " Journey duration: 0:45h Bus:  comes from Cañas ", "time_arr": "06:15", "time_dep": "05:30", "trans_name": "Autotransp. de Upala", "trans_tel": "2470-0197"}, {"date_arr": "thursday", "remarks": " Journey duration: 0:45h Bus:  comes from Cañas ", "time_arr": "07:45", "time_dep": "07:00", "trans_name": "Autotransp. de Upala", "trans_tel": "2470-0197"}, {"date_arr": "thursday", "remarks": " Journey duration: 0:45h Bus:  comes from Cañas ", "time_arr": "10:15", "time_dep": "09:30", "trans_name": "Autotransp. de Upala", "trans_tel": "2470-0197"}, {"date_arr": "thursday", "remarks": " Journey duration: 0:45h Bus:  comes from Cañas ", "time_arr": "13:00", "time_dep": "12:15", "trans_name": "Autotransp. de Upala", "trans_tel": "2470-0197"}, {"date_arr": "thursday", "remarks": " Journey duration: 0:45h Bus:  comes from Cañas ", "time_arr": "14:45", "time_dep": "14:00", "trans_name": "Autotransp. de Upala", "trans_tel": "2470-0197"}, {"date_arr": "thursday", "remarks": " Journey duration: 0:50h Bus ", "time_arr": "15:15", "time_dep": "14:25", "trans_link": "//www.transnortecr.com", "trans_name": "Transnorte de Upala", "trans_tel": "2221-9022"}, {"date_arr": "thursday", "remarks": " Journey duration: 0:45h Bus:  comes from Cañas ", "time_arr": "17:15", "time_dep": "16:30", "trans_name": "Autotransp. de Upala", "trans_tel": "2470-0197"}, {"date_arr": "thursday", "remarks": " Journey duration: 0:45h Bus:  comes from Cañas ", "time_arr": "19:15", "time_dep": "18:30", "trans_name": "Autotransp. de Upala", "trans_tel": "2470-0197"}, {"date_arr": "thursday", "remarks": " Journey duration: 0:50h Bus ", "time_arr": "20:00", "time_dep": "19:10", "trans_link": "//www.transnortecr.com", "trans_name": "Transnorte de Upala", "trans_tel": "2221-9022"}, {"date_arr": "thursday", "remarks": " Journey duration: 0:50h Bus ", "time_arr": "22:10", "time_dep": "21:20", "trans_link": "//www.transnortecr.com", "trans_name": "Transnorte de Upala", "trans_tel": "2221-9022"}], "tuesday": [{"date_arr": "tuesday", "remarks": " Journey duration: 0:45h Bus:  comes from Cañas ", "time_arr": "06:15", "time_dep": "05:30", "trans_name": "Autotransp. de Upala", "trans_tel": "2470-0197"}, {"date_arr": "tuesday", "remarks": " Journey duration: 0:45h Bus:  comes from Cañas ", "time_arr": "07:45", "time_dep": "07:00", "trans_name": "Autotransp. de Upala", "trans_tel": "2470-0197"}, {"date_arr": "tuesday", "remarks": " Journey duration: 0:45h Bus:  comes from Cañas ", "time_arr": "10:15", "time_dep": "09:30", "trans_name": "Autotransp. de Upala", "trans_tel": "2470-0197"}, {"date_arr": "tuesday", "remarks": " Journey duration: 0:45h Bus:  comes from Cañas ", "time_arr": "13:00", "time_dep": "12:15", "trans_name": "Autotransp. de Upala", "trans_tel": "2470-0197"}, {"date_arr": "tuesday", "remarks": " Journey duration: 0:45h Bus:  comes from Cañas ", "time_arr": "14:45", "time_dep": "14:00", "trans_name": "Autotransp. de Upala", "trans_tel": "2470-0197"}, {"date_arr": "tuesday", "remarks": " Journey duration: 0:50h Bus ", "time_arr": "15:15", "time_dep": "14:25", "trans_link": "//www.transnortecr.com", "trans_name": "Transnorte de Upala", "trans_tel": "2221-9022"}, {"date_arr": "tuesday", "remarks": " Journey duration: 0:45h Bus:  comes from Cañas ", "time_arr": "17:15", "time_dep": "16:30", "trans_name": "Autotransp. de Upala", "trans_tel": "2470-0197"}, {"date_arr": "tuesday", "remarks": " Journey duration: 0:45h Bus:  comes from Cañas ", "time_arr": "19:15", "time_dep": "18:30", "trans_name": "Autotransp. de Upala", "trans_tel": "2470-0197"}, {"date_arr": "tuesday", "remarks": " Journey duration: 0:50h Bus ", "time_arr": "20:00", "time_dep": "19:10", "trans_link": "//www.transnortecr.com", "trans_name": "Transnorte de Upala", "trans_tel": "2221-9022"}, {"date_arr": "tuesday", "remarks": " Journey duration: 0:50h Bus ", "time_arr": "22:10", "time_dep": "21:20", "trans_link": "//www.transnortecr.com", "trans_name": "Transnorte de Upala", "trans_tel": "2221-9022"}], "wednesday": [{"date_arr": "wednesday", "remarks": " Journey duration: 0:45h Bus:  comes from Cañas ", "time_arr": "06:15", "time_dep": "05:30", "trans_name": "Autotransp. de Upala", "trans_tel": "2470-0197"}, {"date_arr": "wednesday", "remarks": " Journey duration: 0:45h Bus:  comes from Cañas ", "time_arr": "07:45", "time_dep": "07:00", "trans_name": "Autotransp. de Upala", "trans_tel": "2470-0197"}, {"date_arr": "wednesday", "remarks": " Journey duration: 0:45h Bus:  comes from Cañas ", "time_arr": "10:15", "time_dep": "09:30", "trans_name": "Autotransp. de Upala", "trans_tel": "2470-0197"}, {"date_arr": "wednesday", "remarks": " Journey duration: 0:45h Bus:  comes from Cañas ", "time_arr": "13:00", "time_dep": "12:15", "trans_name": "Autotransp. de Upala", "trans_tel": "2470-0197"}, {"date_arr": "wednesday", "remarks": " Journey duration: 0:45h Bus:  comes from Cañas ", "time_arr": "14:45", "time_dep": "14:00", "trans_name": "Autotransp. de Upala", "trans_tel": "2470-0197"}, {"date_arr": "wednesday", "remarks": " Journey duration: 0:50h Bus ", "time_arr": "15:15", "time_dep": "14:25", "trans_link": "//www.transnortecr.com", "trans_name": "Transnorte de Upala", "trans_tel": "2221-9022"}, {"date_arr": "wednesday", "remarks": " Journey duration: 0:45h Bus:  comes from Cañas ", "time_arr": "17:15", "time_dep": "16:30", "trans_name": "Autotransp. de Upala", "trans_tel": "2470-0197"}, {"date_arr": "wednesday", "remarks": " Journey duration: 0:45h Bus:  comes from Cañas ", "time_arr": "19:15", "time_dep": "18:30", "trans_name": "Autotransp. de Upala", "trans_tel": "2470-0197"}, {"date_arr": "wednesday", "remarks": " Journey duration: 0:50h Bus ", "time_arr": "20:00", "time_dep": "19:10", "trans_link": "//www.transnortecr.com", "trans_name": "Transnorte de Upala", "trans_tel": "2221-9022"}, {"date_arr": "wednesday", "remarks": " Journey duration: 0:50h Bus ", "time_arr": "22:10", "time_dep": "21:20", "trans_link": "//www.transnortecr.com", "trans_name": "Transnorte de Upala", "trans_tel": "2221-9022"}]}}}